{
  "default": "cars",
  "projections" : [
    {
      "name": "cars",
      "dimensions": 12,
      "fields": {
        "color": 3,
        "year": 3,
        "model": 4,
        "manufacturer": 2
      }
    },
    {
      "name": "tweets",
      "doc": "TODO: support full-text search on text field",
      "dimensions": 10,
      "fields": {
        "user.id": 6,
        "user.screen_name": 2,
        "text": 2
      }
    },
    {
      "name": "cloudcmd",
      "dimensions": 12,
      "fields": {
        "fileext": 4,
        "path": 2,
        "filename": 6
      }
    },
    {
      "name": "stocks",
      "dimensions": 12,
      "fields": {
        "symbol": 6,
	"date": 6
      }
    }
  ]
}
